radicl/__init__.py
radicl/api.py
radicl/calibrate.py
radicl/cli.py
radicl/com.py
radicl/commands.py
radicl/gps.py
radicl/high_resolution.py
radicl/interface.py
radicl/plotting.py
radicl/probe.py
radicl/ui_tools.py
radicl/update.py
radicl-0.9.1.dist-info/LICENSE
radicl-0.9.1.dist-info/METADATA
radicl-0.9.1.dist-info/WHEEL
radicl-0.9.1.dist-info/entry_points.txt
radicl-0.9.1.dist-info/top_level.txt
radicl-0.9.1.dist-info/RECORD
