Metadata-Version: 2.1
Name: radicl
Version: 0.9.1
Summary: Command line interface to the Realtime Adventure Data Lyte probe for measuring avalanche conditions
Home-page: https://github.com/adventuredata/radicl
Author: Micah Johnson
Author-email: info@adventuredata.com
License: BSD license
Keywords: radicl
Classifier: Development Status :: 4 - Beta
Classifier: Intended Audience :: Developers
Classifier: License :: OSI Approved :: BSD License
Classifier: Natural Language :: English
Classifier: Programming Language :: Python :: 3.7
Classifier: Programming Language :: Python :: 3.8
Classifier: Programming Language :: Python :: 3.9
License-File: LICENSE
Requires-Dist: pyserial (<4.0.0,>=3.4)
Requires-Dist: pandas (<2.0.0,>=1.2.0)
Requires-Dist: colorama (<0.5.0,>=0.4.3)
Requires-Dist: termcolor (<2.0.0,>=1.1.0)
Requires-Dist: argparse (<2.0.0,>=1.4.0)
Requires-Dist: coloredlogs (<15.0,>=14.0)
Requires-Dist: matplotlib (<4.0.0,>=3.6.0)
Requires-Dist: progressbar2 (<4.0.0,>=3.53.1)
Requires-Dist: study-lyte (>=0.6.2)
Requires-Dist: pynmeagps (==1.0.32)
